specifyplus_cli/__init__.py
specifyplus-0.0.20.dist-info/METADATA
specifyplus-0.0.20.dist-info/WHEEL
specifyplus-0.0.20.dist-info/entry_points.txt
specifyplus-0.0.20.dist-info/licenses/LICENSE
specifyplus-0.0.20.dist-info/RECORD
